{
  "artist_name": "Aviaries",
  "artist_id": "aviaries",
  "seed_source": {
    "origin": "pfc_playlist_scrape",
    "note": "Extracted from 37 PFC editorial playlists"
  },
  "enrichment_timestamp": "2026-02-08T21:20:22.903778+00:00",
  "musicbrainz": {
    "found": true,
    "raw": null,
    "mbid": "0e79a03c-9801-4ec1-af02-6c95823727a7",
    "type": "Group",
    "country": "PL",
    "area": "Poland",
    "begin_date": "2014",
    "end_date": "",
    "gender": "",
    "genres": [],
    "aliases": [],
    "isnis": [],
    "ipis": [],
    "urls": {
      "bandcamp": "https://aviariesband.bandcamp.com/",
      "discogs": "https://www.discogs.com/artist/5083725",
      "social network": "https://www.facebook.com/aviariespl"
    },
    "labels": [
      "Requiem Records"
    ],
    "disambiguation_confidence": "high"
  },
  "deezer": {
    "found": true,
    "raw": null,
    "deezer_id": 55729702,
    "name": "Aviaries",
    "nb_fan": 15,
    "nb_album": 19,
    "link": "https://www.deezer.com/artist/55729702",
    "picture_url": "https://cdn-images.dzcdn.net/images/artist/b7dea078d3ce8ef7dd78d49e5c1bb3b1/250x250-000000-80-0-0.jpg",
    "labels": [],
    "contributors": [],
    "contributor_roles": {},
    "track_titles": [],
    "track_durations": [],
    "track_ranks": [],
    "has_explicit": false,
    "album_types": {
      "album": 2,
      "single": 17
    },
    "albums": [
      {
        "title": "Live From Neurotic Cave",
        "label": "",
        "release_date": "2024-02-01",
        "nb_tracks": 0,
        "type": "album"
      },
      {
        "title": "Aviaries",
        "label": "",
        "release_date": "2016-05-13",
        "nb_tracks": 0,
        "type": "album"
      },
      {
        "title": "Curious Contemplation",
        "label": "",
        "release_date": "2025-05-02",
        "nb_tracks": 0,
        "type": "single"
      },
      {
        "title": "Koi Pond",
        "label": "",
        "release_date": "2025-03-28",
        "nb_tracks": 0,
        "type": "single"
      },
      {
        "title": "Floating Downstream",
        "label": "",
        "release_date": "2025-02-21",
        "nb_tracks": 0,
        "type": "single"
      },
      {
        "title": "Lakeside Dawn",
        "label": "",
        "release_date": "2025-01-10",
        "nb_tracks": 0,
        "type": "single"
      },
      {
        "title": "Forest at Dusk",
        "label": "",
        "release_date": "2024-11-22",
        "nb_tracks": 0,
        "type": "single"
      },
      {
        "title": "Dawn Mist",
        "label": "",
        "release_date": "2024-10-25",
        "nb_tracks": 0,
        "type": "single"
      },
      {
        "title": "Forest Immersion",
        "label": "",
        "release_date": "2024-09-20",
        "nb_tracks": 0,
        "type": "single"
      },
      {
        "title": "Lotus Chimes",
        "label": "",
        "release_date": "2024-08-23",
        "nb_tracks": 0,
        "type": "single"
      },
      {
        "title": "Creek Life",
        "label": "",
        "release_date": "2024-07-26",
        "nb_tracks": 0,
        "type": "single"
      },
      {
        "title": "Winding Path",
        "label": "",
        "release_date": "2024-07-05",
        "nb_tracks": 0,
        "type": "single"
      },
      {
        "title": "Misty Glade",
        "label": "",
        "release_date": "2024-05-17",
        "nb_tracks": 0,
        "type": "single"
      },
      {
        "title": "Overlook",
        "label": "",
        "release_date": "2024-04-19",
        "nb_tracks": 0,
        "type": "single"
      },
      {
        "title": "Songbird Shrine",
        "label": "",
        "release_date": "2024-03-22",
        "nb_tracks": 0,
        "type": "single"
      },
      {
        "title": "Ode To Moss",
        "label": "",
        "release_date": "2024-02-23",
        "nb_tracks": 0,
        "type": "single"
      },
      {
        "title": "Forest Meditation",
        "label": "",
        "release_date": "2024-01-26",
        "nb_tracks": 0,
        "type": "single"
      },
      {
        "title": "Sparrow Coast",
        "label": "",
        "release_date": "2023-12-08",
        "nb_tracks": 0,
        "type": "single"
      },
      {
        "title": "Morning Song, Misty Shores",
        "label": "",
        "release_date": "2023-11-10",
        "nb_tracks": 0,
        "type": "single"
      }
    ],
    "related_artists": []
  },
  "genius": {
    "found": false,
    "raw": null,
    "status": "not_configured"
  },
  "discogs": {
    "found": true,
    "raw": null,
    "discogs_id": 5083725,
    "name": "Aviaries",
    "profile": "Aviaries is a band from Wrocław, Poland. Their music could be described as Cold Wave and New Wave - influenced by Post-Punk.",
    "realname": "",
    "social_urls": [
      "http://www.aviariesband.com/",
      "https://www.facebook.com/aviariespl/",
      "https://aviariesband.bandcamp.com/"
    ],
    "members": [
      "Krzysztof Młyńczak (2)",
      "Mark Magick",
      "Marcin Cieślak",
      "Bartłomiej Kalisz"
    ],
    "groups": [],
    "data_quality": "Needs Vote",
    "physical_releases": 2,
    "digital_only_releases": 8,
    "total_releases": 10,
    "formats": [
      "",
      "14xFile, MP3, Comp, 320",
      "CD, Comp, Ltd, Promo",
      "CD, Comp, Ltd, Promo, Smplr",
      "File, FLAC"
    ],
    "labels": [
      "Not On Label (Aviaries Self-released)",
      "Poule D'Or",
      "Requiem Records"
    ]
  },
  "setlistfm": {
    "found": false,
    "raw": null,
    "status": "not_configured"
  },
  "lastfm": {
    "found": true,
    "raw": null,
    "name": "Aviaries",
    "mbid": "0e79a03c-9801-4ec1-af02-6c95823727a7",
    "listeners": 21546,
    "playcount": 121248,
    "listener_play_ratio": 5.63,
    "bio_exists": true,
    "bio_summary": "There are at least two bands called Aviaries:\n\n1) Wandering through the dark climes of Wroclaw, Poland we happen upon Aviaries – young quartet that boldly burst into scene with massive low and minor key splendor. Moody, liminal, rather pulsing with mystique, Aviaries thread the three strands of new-wave, post-punk and shoegaze. The band’s sound is loomingly full of the conflicted polarities of hope and despair.  \n\nhttps://aviariesband.bandcamp.com/music <a href=\"https://www.last.fm/music/Aviarie",
    "tags": [
      "post-punk",
      "coldwave",
      "shoegaze",
      "electronic",
      "alternative"
    ],
    "similar_artists": [
      "Forest Gold",
      "Yin Gaya",
      "Tonal Topographies",
      "Rani Williams",
      "Caspian Nerida"
    ],
    "top_tracks": [
      {
        "name": "Forest Meditation",
        "listeners": 5901,
        "playcount": 15295
      },
      {
        "name": "Songbird Shrine",
        "listeners": 5822,
        "playcount": 18423
      },
      {
        "name": "Lakeside Dawn",
        "listeners": 4558,
        "playcount": 13103
      },
      {
        "name": "Forest at Dusk",
        "listeners": 3600,
        "playcount": 11833
      },
      {
        "name": "Misty Glade",
        "listeners": 2915,
        "playcount": 8916
      },
      {
        "name": "Curios Contemplation",
        "listeners": 2672,
        "playcount": 7444
      },
      {
        "name": "Winding Path",
        "listeners": 2574,
        "playcount": 6332
      },
      {
        "name": "Ode To Moss",
        "listeners": 2314,
        "playcount": 10121
      },
      {
        "name": "Dawn Mist",
        "listeners": 2023,
        "playcount": 4654
      },
      {
        "name": "Floating Downstream",
        "listeners": 1641,
        "playcount": 6712
      }
    ],
    "url": "https://www.last.fm/music/Aviaries"
  },
  "bandsintown": {
    "found": false,
    "raw": null,
    "status": "not_configured"
  },
  "platforms_found": [
    "musicbrainz",
    "deezer",
    "discogs",
    "lastfm"
  ],
  "platforms_missing": [
    "genius",
    "setlistfm",
    "bandsintown"
  ],
  "platform_count": 4
}