{
  "artist_name": "Debi Nova",
  "artist_id": "debi_nova",
  "seed_source": {
    "origin": "pfc_playlist_scrape",
    "note": "Extracted from 37 PFC editorial playlists"
  },
  "enrichment_timestamp": "2026-02-08T23:26:13.939987+00:00",
  "musicbrainz": {
    "found": true,
    "raw": null,
    "mbid": "551a74e2-fe5c-4923-9a0d-15bc1fd837bd",
    "type": "Person",
    "country": "CR",
    "area": "Costa Rica",
    "begin_date": "1990-08-06",
    "end_date": "",
    "gender": "female",
    "genres": [
      "latin pop",
      "latin"
    ],
    "aliases": [
      "Deborah Nowalski Kader",
      "Debbie Nova"
    ],
    "isnis": [],
    "ipis": [
      "00348872910"
    ],
    "urls": {
      "allmusic": "https://www.allmusic.com/artist/mn0000677245",
      "discogs": "https://www.discogs.com/artist/230758",
      "free streaming": "https://open.spotify.com/artist/5zaG384VZzAb6AMfEnSy2r",
      "IMDb": "https://www.imdb.com/name/nm3878049/",
      "official homepage": "http://debinova.com/",
      "other databases": "https://rateyourmusic.com/artist/debi_nova",
      "social network": "https://www.instagram.com/debinova/",
      "soundcloud": "https://soundcloud.com/debi-nova",
      "streaming": "https://tidal.com/artist/3856013",
      "VIAF": "http://viaf.org/viaf/26458755",
      "wikidata": "https://www.wikidata.org/wiki/Q3364612",
      "youtube": "https://www.youtube.com/user/DebiNovaMusic"
    },
    "labels": [
      "Decca Records",
      "Sony Music",
      "Sony Music | Latin",
      "Altafonte",
      "Universal"
    ],
    "disambiguation_confidence": "high"
  },
  "deezer": {
    "found": true,
    "raw": null,
    "deezer_id": 371600,
    "name": "Debi Nova",
    "nb_fan": 9312,
    "nb_album": 31,
    "link": "https://www.deezer.com/artist/371600",
    "picture_url": "https://cdn-images.dzcdn.net/images/artist/9a3a82b850a1a29065fb018ab8fff04c/250x250-000000-80-0-0.jpg",
    "labels": [],
    "contributors": [
      "Arthur Hanlon",
      "Catalina García",
      "Caztro",
      "Cecile",
      "Franco De Vita",
      "Gaby Moreno",
      "Ha-Ash",
      "Ivy Queen",
      "Kany García",
      "Lupita Infante",
      "Pedro Capó",
      "Sheila E.",
      "Tony Succar",
      "Vicente Garcia"
    ],
    "contributor_roles": {
      "Pedro Capó": [
        "Main"
      ],
      "Kany García": [
        "Main"
      ],
      "Caztro": [
        "Main"
      ],
      "Arthur Hanlon": [
        "Main"
      ],
      "Franco De Vita": [
        "Featured"
      ],
      "Vicente Garcia": [
        "Featured"
      ],
      "Tony Succar": [
        "Main"
      ],
      "Ivy Queen": [
        "Main"
      ],
      "Catalina García": [
        "Main"
      ],
      "Ha-Ash": [
        "Main"
      ],
      "Lupita Infante": [
        "Main"
      ],
      "Gaby Moreno": [
        "Main"
      ],
      "Cecile": [
        "Featured"
      ],
      "Sheila E.": [
        "Featured"
      ]
    },
    "track_titles": [
      "Quédate",
      "Lo Que en Ti Veo",
      "Bolerito",
      "Primera Cita",
      "Bachata Rosa",
      "Tu Manera De Amar",
      "Quizás, Quizás, Quizás",
      "Por Última Vez (feat. Franco de Vita)",
      "No Nos Sobran los Domingos (feat. Vicente García) (Versión Bachata)",
      "No Nos Sobran los Domingos",
      "Barco del Tiempo",
      "Danza Divina / Esta Noche Nunca Sucedió",
      "3:33",
      "Emergencia",
      "No Me Digas Nada",
      "Sigue Asi (Live In Peru)",
      "Superpoderes",
      "We Are Going to Make It Tonight (Outro Jam)",
      "Como Ola en el Mar",
      "Baño De Luna",
      "Quiero Perder La Cabeza",
      "Cupido (feat. Cecile)",
      "Dale Play (feat. Sheila E.)",
      "Primer Beso",
      "Drummer Boy"
    ],
    "track_durations": [
      175,
      205,
      148,
      139,
      210,
      172,
      180,
      249,
      173,
      188,
      235,
      353,
      213,
      251,
      179,
      245,
      195,
      69,
      268,
      158,
      203,
      203,
      198,
      199,
      189
    ],
    "track_ranks": [
      411614,
      130040,
      194910,
      286324,
      281206,
      45815,
      90539,
      237842,
      265714,
      113187,
      137378,
      11650,
      24595,
      21652,
      56917,
      146704,
      33369,
      21819,
      18726,
      191654,
      32558,
      60582,
      70564,
      10227,
      12410
    ],
    "has_explicit": false,
    "album_types": {
      "album": 8,
      "ep": 2,
      "single": 21
    },
    "albums": [
      {
        "title": "Todo Puede Convertirse en Canción",
        "label": "",
        "release_date": "2025-07-18",
        "nb_tracks": 0,
        "type": "album"
      },
      {
        "title": "Dar Vida",
        "label": "",
        "release_date": "2024-05-23",
        "nb_tracks": 0,
        "type": "album"
      },
      {
        "title": "En Vivo Desde El Teatro Nacional De Costa Rica",
        "label": "",
        "release_date": "2021-07-30",
        "nb_tracks": 0,
        "type": "album"
      },
      {
        "title": "3:33",
        "label": "",
        "release_date": "2020-05-22",
        "nb_tracks": 0,
        "type": "album"
      },
      {
        "title": "Gran Ciudad",
        "label": "",
        "release_date": "2017-03-31",
        "nb_tracks": 0,
        "type": "album"
      },
      {
        "title": "Soy",
        "label": "",
        "release_date": "2014-06-30",
        "nb_tracks": 0,
        "type": "album"
      },
      {
        "title": "Luna Nueva (Versión En Español)",
        "label": "",
        "release_date": "2010-05-18",
        "nb_tracks": 0,
        "type": "album"
      },
      {
        "title": "Luna Nueva (Bonus Track Version)",
        "label": "",
        "release_date": "2010-05-18",
        "nb_tracks": 0,
        "type": "album"
      },
      {
        "title": "Dar Vida - B Sides",
        "label": "",
        "release_date": "2024-09-10",
        "nb_tracks": 0,
        "type": "ep"
      },
      {
        "title": "Un Día a la Vez",
        "label": "",
        "release_date": "2013-12-17",
        "nb_tracks": 0,
        "type": "ep"
      },
      {
        "title": "Holograma",
        "label": "",
        "release_date": "2025-05-30",
        "nb_tracks": 0,
        "type": "single"
      },
      {
        "title": "Se Va",
        "label": "",
        "release_date": "2025-05-09",
        "nb_tracks": 0,
        "type": "single"
      },
      {
        "title": "Tu Manera De Amar",
        "label": "",
        "release_date": "2025-03-28",
        "nb_tracks": 0,
        "type": "single"
      },
      {
        "title": "Primera Cita",
        "label": "",
        "release_date": "2024-09-12",
        "nb_tracks": 0,
        "type": "single"
      },
      {
        "title": "Going to Bocas",
        "label": "",
        "release_date": "2024-05-20",
        "nb_tracks": 0,
        "type": "single"
      },
      {
        "title": "Barco del Tiempo",
        "label": "",
        "release_date": "2024-05-01",
        "nb_tracks": 0,
        "type": "single"
      },
      {
        "title": "Primer Beso",
        "label": "",
        "release_date": "2024-04-04",
        "nb_tracks": 0,
        "type": "single"
      },
      {
        "title": "Pasajera",
        "label": "",
        "release_date": "2025-02-03",
        "nb_tracks": 0,
        "type": "single"
      },
      {
        "title": "Baño De Luna",
        "label": "",
        "release_date": "2023-09-21",
        "nb_tracks": 0,
        "type": "single"
      },
      {
        "title": "Quizás, Quizás, Quizás",
        "label": "",
        "release_date": "2022-11-23",
        "nb_tracks": 0,
        "type": "single"
      },
      {
        "title": "Luciérnagas",
        "label": "",
        "release_date": "2022-05-27",
        "nb_tracks": 0,
        "type": "single"
      },
      {
        "title": "Superpoderes",
        "label": "",
        "release_date": "2020-03-06",
        "nb_tracks": 0,
        "type": "single"
      },
      {
        "title": "Quédate",
        "label": "",
        "release_date": "2019-11-22",
        "nb_tracks": 0,
        "type": "single"
      },
      {
        "title": "Bola de Cristal (Versión Acústica)",
        "label": "",
        "release_date": "2018-07-20",
        "nb_tracks": 0,
        "type": "single"
      },
      {
        "title": "No Nos Sobran los Domingos (feat. Vicente García) (Versión Bachata)",
        "label": "",
        "release_date": "2018-02-09",
        "nb_tracks": 0,
        "type": "single"
      },
      {
        "title": "Al Frente (Versión Acústica)",
        "label": "",
        "release_date": "2018-01-15",
        "nb_tracks": 0,
        "type": "single"
      },
      {
        "title": "Gran Ciudad (Barzo Remix)",
        "label": "",
        "release_date": "2017-07-28",
        "nb_tracks": 0,
        "type": "single"
      },
      {
        "title": "Dale Play (feat. Sheila E.) (Printz Board Remix)",
        "label": "",
        "release_date": "2017-04-28",
        "nb_tracks": 0,
        "type": "single"
      },
      {
        "title": "Volver a Comenzar (Primero de Enero)",
        "label": "",
        "release_date": "2016-01-01",
        "nb_tracks": 0,
        "type": "single"
      },
      {
        "title": "Como Ola En El Mar",
        "label": "",
        "release_date": "2014-10-06",
        "nb_tracks": 0,
        "type": "single"
      }
    ],
    "related_artists": [
      "Tommy Torres",
      "Kany Garcia",
      "Santiago Cruz",
      "Antonio José",
      "Manuel Medrano",
      "Noel Schajris",
      "Malú",
      "Arevalo",
      "Mike Bahia",
      "Kurt"
    ]
  },
  "genius": {
    "found": false,
    "raw": null,
    "status": "not_configured"
  },
  "discogs": {
    "found": true,
    "raw": null,
    "discogs_id": 230758,
    "name": "Debi Nova",
    "profile": "Costa Rican singer-songwriter who resides in Los Angeles.",
    "realname": "Deborah Nowalski Kader",
    "social_urls": [
      "http://debinova.com/",
      "https://soundcloud.com/debi-nova",
      "https://www.youtube.com/user/DebiNovaMusic",
      "https://www.facebook.com/debinovamusic",
      "https://www.instagram.com/debinova/",
      "https://twitter.com/debinova"
    ],
    "members": [],
    "groups": [],
    "data_quality": "Needs Vote",
    "physical_releases": 52,
    "digital_only_releases": 47,
    "total_releases": 99,
    "formats": [
      "",
      "12\"",
      "12\", Ltd, Promo, Smplr",
      "12\", Promo",
      "12\", Promo, Smplr",
      "12xFile, AAC, Album, 256",
      "2xCD, Comp",
      "2xCD, Comp, Promo",
      "2xCD, Mixed",
      "2xCDr, Mixed",
      "3xCD, Mixed, Mixtape, Promo",
      "5xFile, MP3, EP, 260",
      "8xFile, AIFF, Album, S/Edition",
      "CD, Album",
      "CD, Album, Dig",
      "CD, Album, RE + CD, Album, RE + Comp",
      "CD, Comp",
      "CD, Comp, Mixed, Promo",
      "CD, Comp, Promo",
      "CD, Comp, Smplr",
      "CD, EP, Promo",
      "CD, Ltd, Mixed",
      "CD, Mixed",
      "CD, Mixed, Promo, Smplr",
      "CD, Mixed, S/Edition",
      "CD, Promo, Smplr",
      "CDr, Comp, Promo",
      "CDr, Enh, Promo",
      "CDr, Ltd, Mixed, Promo",
      "CDr, Mixed, Mixtape, Promo",
      "CDr, Single, Dig",
      "DVD, Comp, Promo",
      "DVD-V, Comp",
      "DVD-V, Comp, Promo",
      "DVD-V, Comp, Unofficial, PAL",
      "File, AAC, Single",
      "File, AIFF, FLAC, MP3, WAV, Single",
      "File, FLAC, Single",
      "File, MP3, Comp, Mixed",
      "File, MP3, Mixtape, 320",
      "File, MP3, WAV, Single",
      "LP, Album",
      "LP, Comp, Red"
    ],
    "labels": [
      "A&M Records",
      "Ana Free Music",
      "Atlantic, Rhino Records (2)",
      "Bong Bros.",
      "Concord Records",
      "Cornerstone Promotion",
      "DLIP Records",
      "DMC",
      "Delicious Vinyl, ORG Music",
      "Digiwaxx",
      "Disk Union",
      "Downtown Records (8)",
      "E Genesis Group",
      "Eckō Unltd., Digiwaxx",
      "Elektra",
      "Filter Magazine",
      "Greensleeves Records",
      "ICE Records (4)",
      "Intolerancia",
      "Jazz Gangsters, MondayJazz",
      "Jazziz",
      "Kannon Entertainment",
      "Lácteo Cósmico",
      "M6 Music Label",
      "Marnier-Lapostolle Inc.",
      "Music Factory",
      "Music Response",
      "Not On Label",
      "Not On Label (InSax Self-released)",
      "Not On Label (Pete Escovedo Self-released)",
      "Pro Motion",
      "Promo Only",
      "Roc-A-Fella Records",
      "Royalty (2)",
      "Scion Audio/Visual",
      "Sleep Records (2)",
      "Sleeping Giant Music",
      "Sony Music",
      "Sony Music Entertainment (Central America) S.A.",
      "Sony Music Latin",
      "Souled Out Radio",
      "Street Video Studios",
      "Surco, Decca",
      "TLP Musica Records",
      "TM Century",
      "Universal",
      "Universal Music",
      "Universal Music Publishing Group",
      "Warner Bros. Records",
      "Warner Music Canada, Hi-Bias Records"
    ]
  },
  "setlistfm": {
    "found": false,
    "raw": null,
    "status": "not_configured"
  },
  "lastfm": {
    "found": true,
    "raw": null,
    "name": "Debi Nova",
    "mbid": "551a74e2-fe5c-4923-9a0d-15bc1fd837bd",
    "listeners": 30083,
    "playcount": 301675,
    "listener_play_ratio": 10.03,
    "bio_exists": true,
    "bio_summary": "Debi Nova is a multi-talented female vocalist from Escazu, Costa Rica who calls Los Angeles, California home. A graduate of The Los Angeles Music Academy, Nova has graced her signature voice on various projects from jazz artist Boney James to rapper Q-Tip to Sergio Mendes and Will.I.AM of the Black Eyed Peas. Her single CD, \"One Rhythm\", has an English version, Spanish version, and six mixes, all in advance of her anticipated 13 song future CD.\n\nShe also callaborated with Ricky Martin in his eng",
    "tags": [
      "pop",
      "female vocalists",
      "costa rica",
      "latin",
      "soul"
    ],
    "similar_artists": [
      "Malpaís",
      "Cocofunka",
      "Jeudy García",
      "424",
      "Suite Doble"
    ],
    "top_tracks": [
      {
        "name": "Quédate",
        "listeners": 6700,
        "playcount": 31282
      },
      {
        "name": "Drummer Boy",
        "listeners": 6035,
        "playcount": 55568
      },
      {
        "name": "Por Última Vez (feat. Franco de Vita)",
        "listeners": 3076,
        "playcount": 9897
      },
      {
        "name": "Como Ola En El Mar",
        "listeners": 2133,
        "playcount": 5435
      },
      {
        "name": "No Nos Sobran los Domingos (feat. Vicente García) - Versión Bachata",
        "listeners": 2049,
        "playcount": 8601
      },
      {
        "name": "Superpoderes",
        "listeners": 1328,
        "playcount": 6731
      },
      {
        "name": "3:33",
        "listeners": 1262,
        "playcount": 11388
      },
      {
        "name": "No Nos Sobran los Domingos - Versión Bachata",
        "listeners": 1061,
        "playcount": 2869
      },
      {
        "name": "Something To Believe In",
        "listeners": 1040,
        "playcount": 2528
      },
      {
        "name": "Bola de Cristal - Versión Acústica",
        "listeners": 881,
        "playcount": 2196
      }
    ],
    "url": "https://www.last.fm/music/Debi+Nova"
  },
  "bandsintown": {
    "found": false,
    "raw": null,
    "status": "not_configured"
  },
  "platforms_found": [
    "musicbrainz",
    "deezer",
    "discogs",
    "lastfm"
  ],
  "platforms_missing": [
    "genius",
    "setlistfm",
    "bandsintown"
  ],
  "platform_count": 4
}