{
  "artist_name": "Jordan Rakei",
  "artist_id": "jordan_rakei",
  "seed_source": {
    "origin": "pfc_playlist_scrape",
    "note": "Extracted from 37 PFC editorial playlists"
  },
  "enrichment_timestamp": "2026-02-09T14:36:31.802067+00:00",
  "musicbrainz": {
    "found": true,
    "raw": null,
    "mbid": "812c46e5-3d65-4e80-ada8-269450c5621b",
    "type": "Person",
    "country": "",
    "area": "London",
    "begin_date": "",
    "end_date": "",
    "gender": "male",
    "genres": [
      "r&b",
      "alternative r&b",
      "r&b/soul",
      "neosoul",
      "soul",
      "reggae"
    ],
    "aliases": [],
    "isnis": [
      "0000000463195423"
    ],
    "ipis": [],
    "urls": {
      "allmusic": "https://www.allmusic.com/artist/mn0003319054",
      "bandcamp": "https://jordanrakei.bandcamp.com/",
      "discogs": "https://www.discogs.com/artist/3914757",
      "free streaming": "https://www.deezer.com/artist/6581343",
      "last.fm": "https://www.last.fm/music/Jordan+Rakei",
      "official homepage": "https://www.jordanrakei.com/",
      "other databases": "https://rateyourmusic.com/artist/jordan-rakei",
      "purchase for download": "https://music.apple.com/us/artist/705284964",
      "social network": "https://www.instagram.com/jrakz/",
      "songkick": "https://www.songkick.com/artists/7562719",
      "soundcloud": "https://soundcloud.com/jordan-rakei",
      "streaming": "https://tidal.com/artist/5978731",
      "wikidata": "https://www.wikidata.org/wiki/Q55583815",
      "youtube": "https://www.youtube.com/user/jordanrakei"
    },
    "labels": [
      "Decca Records",
      "Decca Classics",
      "Twin Music Incorporation",
      "Ninja Tune",
      "Apple Music",
      "BBC Radio 6 Music",
      "LateNightTales",
      "Fontana",
      "Night Time Stories",
      "Warner Records",
      "4101 Records",
      "Bossy Music",
      "Late Night Tales"
    ],
    "disambiguation_confidence": "high"
  },
  "deezer": {
    "found": true,
    "raw": null,
    "deezer_id": 6581343,
    "name": "Jordan Rakei",
    "nb_fan": 16384,
    "nb_album": 55,
    "link": "https://www.deezer.com/artist/6581343",
    "picture_url": "https://cdn-images.dzcdn.net/images/artist/50e583a149e1636ce4a707723fd74d2d/250x250-000000-80-0-0.jpg",
    "labels": [],
    "contributors": [
      "Gwen Bunn",
      "Jalen Ngonda",
      "Loyle Carner",
      "Tom Misch"
    ],
    "contributor_roles": {
      "Loyle Carner": [
        "Main"
      ],
      "Tom Misch": [
        "Main"
      ],
      "Jalen Ngonda": [
        "Main"
      ],
      "Gwen Bunn": [
        "Featured"
      ]
    },
    "track_titles": [
      "Flowers",
      "Ottolenghi",
      "Family (Acoustic)",
      "Midnight Mischief (Tom Misch Remix)",
      "The Seize",
      "Blame It on the Youth",
      "Midnight Mischief",
      "The Light",
      "Chemical Coincidence",
      "Eye To Eye",
      "Family",
      "Friend or Foe",
      "Mind’s Eye",
      "Alright",
      "Defection",
      "Talk Talk Talk",
      "Add the Bassline",
      "Carnation",
      "What It Gave Me",
      "Sorceress",
      "Street Light",
      "Nerve",
      "Best Part (BBC Maida Vale Session)",
      "Lucid",
      "Goodbyes"
    ],
    "track_durations": [
      249,
      197,
      238,
      266,
      214,
      154,
      322,
      240,
      213,
      351,
      207,
      250,
      246,
      275,
      245,
      234,
      153,
      239,
      165,
      183,
      249,
      235,
      203,
      292,
      296
    ],
    "track_ranks": [
      510423,
      562806,
      422516,
      466092,
      363926,
      154481,
      293799,
      207365,
      193633,
      314970,
      415000,
      290595,
      250223,
      315162,
      394441,
      288096,
      212152,
      129954,
      529403,
      226276,
      138261,
      289065,
      197732,
      240033,
      278427
    ],
    "has_explicit": false,
    "album_types": {
      "album": 9,
      "ep": 5,
      "single": 40,
      "compile": 1
    },
    "albums": [
      {
        "title": "Live From The Royal Albert Hall",
        "label": "",
        "release_date": "2025-07-25",
        "nb_tracks": 0,
        "type": "album"
      },
      {
        "title": "The Loop",
        "label": "",
        "release_date": "2024-05-10",
        "nb_tracks": 0,
        "type": "album"
      },
      {
        "title": "The Loop (Deluxe)",
        "label": "",
        "release_date": "2025-04-04",
        "nb_tracks": 0,
        "type": "album"
      },
      {
        "title": "What We Call Life",
        "label": "",
        "release_date": "2021-09-17",
        "nb_tracks": 0,
        "type": "album"
      },
      {
        "title": "Late Night Tales: Jordan Rakei (Lnt Mix)",
        "label": "",
        "release_date": "2021-04-09",
        "nb_tracks": 0,
        "type": "album"
      },
      {
        "title": "Origin",
        "label": "",
        "release_date": "2019-06-14",
        "nb_tracks": 0,
        "type": "album"
      },
      {
        "title": "Origin (Deluxe Edition)",
        "label": "",
        "release_date": "2020-03-13",
        "nb_tracks": 0,
        "type": "album"
      },
      {
        "title": "Wallflower",
        "label": "",
        "release_date": "2017-09-22",
        "nb_tracks": 0,
        "type": "album"
      },
      {
        "title": "Cloak",
        "label": "",
        "release_date": "2016-06-03",
        "nb_tracks": 0,
        "type": "album"
      },
      {
        "title": "Bruises",
        "label": "",
        "release_date": "2022-03-04",
        "nb_tracks": 0,
        "type": "ep"
      },
      {
        "title": "Live in Session",
        "label": "",
        "release_date": "2017-10-25",
        "nb_tracks": 0,
        "type": "ep"
      },
      {
        "title": "Nerve EP",
        "label": "",
        "release_date": "2017-08-22",
        "nb_tracks": 0,
        "type": "ep"
      },
      {
        "title": "Rooftops (Remixes)",
        "label": "",
        "release_date": "2017-02-03",
        "nb_tracks": 0,
        "type": "ep"
      },
      {
        "title": "Groove Curse",
        "label": "",
        "release_date": "2014-08-15",
        "nb_tracks": 0,
        "type": "ep"
      },
      {
        "title": "What It Gave Me",
        "label": "",
        "release_date": "2025-11-27",
        "nb_tracks": 0,
        "type": "single"
      },
      {
        "title": "Clouds (Live From The Royal Albert Hall)",
        "label": "",
        "release_date": "2025-07-09",
        "nb_tracks": 0,
        "type": "single"
      },
      {
        "title": "Eye To Eye (Live From The Royal Albert Hall)",
        "label": "",
        "release_date": "2025-06-13",
        "nb_tracks": 0,
        "type": "single"
      },
      {
        "title": "The Seize",
        "label": "",
        "release_date": "2025-03-14",
        "nb_tracks": 0,
        "type": "single"
      },
      {
        "title": "Talk Talk Talk",
        "label": "",
        "release_date": "2025-02-18",
        "nb_tracks": 0,
        "type": "single"
      },
      {
        "title": "Celebrate",
        "label": "",
        "release_date": "2024-11-08",
        "nb_tracks": 0,
        "type": "single"
      },
      {
        "title": "Hopes and Dreams (Abbey Road After Hours Session)",
        "label": "",
        "release_date": "2024-10-04",
        "nb_tracks": 0,
        "type": "single"
      },
      {
        "title": "Friend or Foe",
        "label": "",
        "release_date": "2024-04-05",
        "nb_tracks": 0,
        "type": "single"
      },
      {
        "title": "Learning",
        "label": "",
        "release_date": "2024-03-01",
        "nb_tracks": 0,
        "type": "single"
      },
      {
        "title": "Freedom",
        "label": "",
        "release_date": "2024-01-22",
        "nb_tracks": 0,
        "type": "single"
      },
      {
        "title": "Flowers",
        "label": "",
        "release_date": "2023-10-26",
        "nb_tracks": 0,
        "type": "single"
      },
      {
        "title": "Bruises",
        "label": "",
        "release_date": "2022-02-10",
        "nb_tracks": 0,
        "type": "single"
      },
      {
        "title": "Live at Metropolis Studios",
        "label": "",
        "release_date": "2021-11-15",
        "nb_tracks": 0,
        "type": "single"
      },
      {
        "title": "Unguarded",
        "label": "",
        "release_date": "2021-08-31",
        "nb_tracks": 0,
        "type": "single"
      },
      {
        "title": "Clouds",
        "label": "",
        "release_date": "2021-08-19",
        "nb_tracks": 0,
        "type": "single"
      },
      {
        "title": "Send My Love",
        "label": "",
        "release_date": "2021-08-04",
        "nb_tracks": 0,
        "type": "single"
      }
    ],
    "related_artists": [
      "Tom Misch",
      "Yazmin Lacey",
      "Joy Crookes",
      "Moonchild",
      "Joesef",
      "Hiatus Kaiyote",
      "Aaron Taylor",
      "Sault",
      "Lianne La Havas",
      "Maverick Sabre"
    ]
  },
  "genius": {
    "found": false,
    "raw": null,
    "status": "not_configured"
  },
  "discogs": {
    "found": true,
    "raw": null,
    "discogs_id": 3914757,
    "name": "Jordan Rakei",
    "profile": "New Zealand musician, producer, singer and songwriter, born 23 May 1992 in Tokoroa, raised in Brisbane and based in London. ",
    "realname": "Jordan Rakei",
    "social_urls": [
      "https://www.jordanrakei.com/",
      "https://www.facebook.com/JordanRakei/",
      "https://twitter.com/jordanrakei",
      "https://www.instagram.com/jrakz/",
      "https://soundcloud.com/jordan-rakei",
      "https://jordanrakei.bandcamp.com/",
      "https://www.youtube.com/user/jordanrakei",
      "https://www.audioculture.co.nz/profile/jordan-rakei",
      "https://en.wikipedia.org/wiki/Jordan_Rakei"
    ],
    "members": [],
    "groups": [],
    "data_quality": "Needs Vote",
    "physical_releases": 32,
    "digital_only_releases": 68,
    "total_releases": 100,
    "formats": [
      "",
      "10\", Ltd, Yel",
      "12\"",
      "12\", EP",
      "12\", EP, Ltd",
      "12\", EP, Ltd, 180",
      "12xFile, FLAC, Album",
      "17xFile, FLAC, Album, Comp, Dlx, 24b",
      "21xFile, AAC, Album",
      "2xCD, Comp",
      "2xCD, Comp, Promo, Smplr",
      "2xFile, WAV, Single",
      "2xLP",
      "2xLP, Comp",
      "4xFile, FLAC, EP",
      "4xFile, MP3, EP",
      "6xCD, Comp + Box",
      "6xLP, Ltd + Box, Ltd",
      "7\", Ltd",
      "Box, Comp, Mixed + 7xCDr, Comp, Mixed",
      "CD, Comp, Dig",
      "CD, Comp, Mixed",
      "CD, Comp, Promo",
      "CD, Comp, Promo, Smplr",
      "CD, EP",
      "CDr, Car",
      "CDr, EP",
      "CDr, Promo",
      "CDr, Single, Promo",
      "File, AAC, Single, 256",
      "File, AIFF, MP3, WAV",
      "File, FLAC",
      "File, FLAC, Single",
      "File, MP3, 320",
      "File, MP3, Single, 320",
      "LP, EP, RP + LP, EP, RP + 7\", Ltd + Comp, Dlx, RP",
      "LP, Ltd, Pic, S/Edition + 2xLP + Flexi, 7\", S/Side"
    ],
    "labels": [
      "A440 Entertainment",
      "AMF Records (3), Virgin EMI Records",
      "Decca",
      "Decca (UMO)",
      "EMI",
      "Equinox Recordings (5)",
      "Fine Line Records (6)",
      "Future Classic, Hw&W Recordings",
      "House Of Beige",
      "Magic Records",
      "Middle Name Records",
      "Ninja Tune",
      "Not On Label",
      "Not On Label (DJ Sabrina The Teenage DJ Self-released)",
      "Not On Label (LHA (Leehahn & Adikkal) Self-released)",
      "Nova Records, Wagram Music",
      "P-Vine Records",
      "P-Vine Records, Tower Records Japan Inc.",
      "Pink Bird Recording Co.",
      "Redkliff Records",
      "Rhythm Section International",
      "Since '93",
      "Soul Bag (2)",
      "Soul Has No Tempo",
      "Wagram Music"
    ]
  },
  "setlistfm": {
    "found": false,
    "raw": null,
    "status": "not_configured"
  },
  "lastfm": {
    "found": true,
    "raw": null,
    "name": "Jordan Rakei",
    "mbid": "812c46e5-3d65-4e80-ada8-269450c5621b",
    "listeners": 375892,
    "playcount": 6270631,
    "listener_play_ratio": 16.68,
    "bio_exists": true,
    "bio_summary": "Jordan Rakei, now based in London, started his career in 2012 playing keyboards in many acts around Brisbane and New Zealand. He self-released his debut six-track EP Franklin' s Room, in September 2013 followed by Groove Course in August 2014 through Soul has no tempo. He also featured on the FKJ song 'Learn to fly'. In 2015, he featured on 'Sunrise / Beautiful' by Ta-Ku, 'Wake Up This Day' by Tom Misch and 'Masterpiece' by Disclosure. \n\n'The light' and 'Talk to me' were released as an advance o",
    "tags": [
      "soul",
      "rnb",
      "Neo-Soul",
      "jazz",
      "electronica"
    ],
    "similar_artists": [
      "Tom Misch",
      "Aaron Taylor",
      "Oscar Jerome",
      "Charlotte Day Wilson",
      "Moonchild"
    ],
    "top_tracks": [
      {
        "name": "Midnight Mischief - Tom Misch Remix",
        "listeners": 80821,
        "playcount": 535304
      },
      {
        "name": "Borderline",
        "listeners": 56138,
        "playcount": 277815
      },
      {
        "name": "Family",
        "listeners": 53434,
        "playcount": 202938
      },
      {
        "name": "Midnight Mischief (Tom Misch Remix)",
        "listeners": 51539,
        "playcount": 271992
      },
      {
        "name": "Mind’s Eye",
        "listeners": 51152,
        "playcount": 233062
      },
      {
        "name": "Alright",
        "listeners": 50945,
        "playcount": 223194
      },
      {
        "name": "Add the Bassline",
        "listeners": 50776,
        "playcount": 186832
      },
      {
        "name": "Say Something",
        "listeners": 44377,
        "playcount": 156631
      },
      {
        "name": "Wind Parade",
        "listeners": 38971,
        "playcount": 143881
      },
      {
        "name": "Signs",
        "listeners": 36957,
        "playcount": 143558
      }
    ],
    "url": "https://www.last.fm/music/Jordan+Rakei"
  },
  "bandsintown": {
    "found": false,
    "raw": null,
    "status": "not_configured"
  },
  "platforms_found": [
    "musicbrainz",
    "deezer",
    "discogs",
    "lastfm"
  ],
  "platforms_missing": [
    "genius",
    "setlistfm",
    "bandsintown"
  ],
  "platform_count": 4
}