{
  "artist_name": "Lone Tusker",
  "artist_id": "lone_tusker",
  "seed_source": {
    "origin": "pfc_playlist_scrape",
    "note": "Extracted from 37 PFC editorial playlists"
  },
  "enrichment_timestamp": "2026-02-09T15:11:31.337331+00:00",
  "musicbrainz": {
    "found": true,
    "raw": null,
    "mbid": "be37ed6a-4989-402f-9838-cef9e412f35e",
    "type": "Person",
    "country": "",
    "area": "",
    "begin_date": "",
    "end_date": "",
    "gender": "male",
    "genres": [
      "electronic",
      "deep house"
    ],
    "aliases": [],
    "isnis": [],
    "ipis": [],
    "urls": {
      "free streaming": "https://open.spotify.com/artist/3vlH5PSk5GSm61lfafSPAl",
      "social network": "https://twitter.com/lonetuskermusic",
      "soundcloud": "https://soundcloud.com/lonetuskermusic"
    },
    "labels": [
      "Lone Tusker",
      "Gahara",
      "[no label]"
    ],
    "disambiguation_confidence": "high"
  },
  "deezer": {
    "found": true,
    "raw": null,
    "deezer_id": 14718919,
    "name": "Lone Tusker",
    "nb_fan": 230,
    "nb_album": 79,
    "link": "https://www.deezer.com/artist/14718919",
    "picture_url": "https://cdn-images.dzcdn.net/images/artist/7850f4eb217e3f2bd9831634da5619de/250x250-000000-80-0-0.jpg",
    "labels": [],
    "contributors": [
      "Alberto Ciccarini",
      "Angie Robba",
      "Axway",
      "Ben Woodward",
      "DALEXO",
      "Foínix",
      "Jessi G",
      "Jethro",
      "Marc Robillard",
      "Paul Hawksworth",
      "Poul",
      "SHKHR",
      "Santi",
      "Tim Goldn",
      "Ugg'A",
      "Victoria McCartney"
    ],
    "contributor_roles": {
      "Foínix": [
        "Main"
      ],
      "Jethro": [
        "Main"
      ],
      "Jessi G": [
        "Main"
      ],
      "Ugg'A": [
        "Main"
      ],
      "SHKHR": [
        "Main"
      ],
      "Victoria McCartney": [
        "Main"
      ],
      "Santi": [
        "Main"
      ],
      "Paul Hawksworth": [
        "Main"
      ],
      "Axway": [
        "Main"
      ],
      "Ben Woodward": [
        "Featured"
      ],
      "DALEXO": [
        "Main"
      ],
      "Angie Robba": [
        "Main"
      ],
      "Tim Goldn": [
        "Main"
      ],
      "Alberto Ciccarini": [
        "Main"
      ],
      "Poul": [
        "Main"
      ],
      "Marc Robillard": [
        "Main"
      ]
    },
    "track_titles": [
      "No Sleep",
      "Birds Of A Feather",
      "Stumblin' In",
      "Sweater Weather",
      "Coastline",
      "Runaway",
      "YUKON",
      "Diet Pepsi",
      "Chase The Sun",
      "A Bar Song (Tipsy)",
      "Mirrors",
      "Aicha",
      "Smooth Operator",
      "No Diggity",
      "Crazy",
      "Green",
      "Peaches",
      "Anti-Hero (feat. Ben Woodward)",
      "You're Somebody Else",
      "Cigarette Daydreams",
      "Don't Stop Believin'",
      "Wicked Game",
      "Miracle",
      "Invisible",
      "Rolling Down"
    ],
    "track_durations": [
      176,
      187,
      177,
      154,
      188,
      178,
      147,
      146,
      163,
      134,
      194,
      152,
      186,
      162,
      181,
      159,
      169,
      159,
      158,
      151,
      148,
      162,
      165,
      158,
      172
    ],
    "track_ranks": [
      283686,
      439326,
      452330,
      313097,
      249593,
      283677,
      213303,
      343100,
      174591,
      364030,
      286801,
      113822,
      423615,
      293474,
      282268,
      90215,
      100491,
      67633,
      350400,
      259254,
      306323,
      226137,
      226232,
      76236,
      156713
    ],
    "has_explicit": false,
    "album_types": {
      "single": 79
    },
    "albums": [
      {
        "title": "YUKON",
        "label": "",
        "release_date": "2026-01-16",
        "nb_tracks": 0,
        "type": "single"
      },
      {
        "title": "Fingerprints",
        "label": "",
        "release_date": "2025-12-26",
        "nb_tracks": 0,
        "type": "single"
      },
      {
        "title": "Chase the Sun",
        "label": "",
        "release_date": "2025-10-17",
        "nb_tracks": 0,
        "type": "single"
      },
      {
        "title": "Chase The Sun",
        "label": "",
        "release_date": "2025-10-17",
        "nb_tracks": 0,
        "type": "single"
      },
      {
        "title": "Coastline",
        "label": "",
        "release_date": "2025-07-25",
        "nb_tracks": 0,
        "type": "single"
      },
      {
        "title": "Coastline",
        "label": "",
        "release_date": "2025-07-25",
        "nb_tracks": 0,
        "type": "single"
      },
      {
        "title": "Cigarette Daydreams",
        "label": "",
        "release_date": "2025-05-30",
        "nb_tracks": 0,
        "type": "single"
      },
      {
        "title": "Diet Pepsi",
        "label": "",
        "release_date": "2025-04-18",
        "nb_tracks": 0,
        "type": "single"
      },
      {
        "title": "That's So True",
        "label": "",
        "release_date": "2025-03-28",
        "nb_tracks": 0,
        "type": "single"
      },
      {
        "title": "So Sick (feat. Eugeene)",
        "label": "",
        "release_date": "2025-03-07",
        "nb_tracks": 0,
        "type": "single"
      },
      {
        "title": "BITTERSUITE",
        "label": "",
        "release_date": "2025-02-07",
        "nb_tracks": 0,
        "type": "single"
      },
      {
        "title": "Love To Lose",
        "label": "",
        "release_date": "2025-01-24",
        "nb_tracks": 0,
        "type": "single"
      },
      {
        "title": "A Bar Song (Tipsy)",
        "label": "",
        "release_date": "2025-01-10",
        "nb_tracks": 0,
        "type": "single"
      },
      {
        "title": "Don't Stop Believin'",
        "label": "",
        "release_date": "2024-12-27",
        "nb_tracks": 0,
        "type": "single"
      },
      {
        "title": "Little Monsters (feat. REDV)",
        "label": "",
        "release_date": "2024-09-27",
        "nb_tracks": 0,
        "type": "single"
      },
      {
        "title": "Geordie",
        "label": "",
        "release_date": "2024-09-06",
        "nb_tracks": 0,
        "type": "single"
      },
      {
        "title": "Too Sweet",
        "label": "",
        "release_date": "2024-08-16",
        "nb_tracks": 0,
        "type": "single"
      },
      {
        "title": "Birds Of A Feather",
        "label": "",
        "release_date": "2024-08-02",
        "nb_tracks": 0,
        "type": "single"
      },
      {
        "title": "Stumblin' In",
        "label": "",
        "release_date": "2024-06-28",
        "nb_tracks": 0,
        "type": "single"
      },
      {
        "title": "What Is Love",
        "label": "",
        "release_date": "2024-06-21",
        "nb_tracks": 0,
        "type": "single"
      },
      {
        "title": "We Can't Be Friends",
        "label": "",
        "release_date": "2024-05-17",
        "nb_tracks": 0,
        "type": "single"
      },
      {
        "title": "We Can't Be Friends",
        "label": "",
        "release_date": "2024-05-17",
        "nb_tracks": 0,
        "type": "single"
      },
      {
        "title": "Runaway",
        "label": "",
        "release_date": "2024-04-26",
        "nb_tracks": 0,
        "type": "single"
      },
      {
        "title": "Locked Away",
        "label": "",
        "release_date": "2024-04-05",
        "nb_tracks": 0,
        "type": "single"
      },
      {
        "title": "Silence",
        "label": "",
        "release_date": "2024-03-29",
        "nb_tracks": 0,
        "type": "single"
      },
      {
        "title": "Fireflies",
        "label": "",
        "release_date": "2024-03-22",
        "nb_tracks": 0,
        "type": "single"
      },
      {
        "title": "No Sleep",
        "label": "",
        "release_date": "2024-02-09",
        "nb_tracks": 0,
        "type": "single"
      },
      {
        "title": "...What About Now? (feat. Josh Reflex)",
        "label": "",
        "release_date": "2023-12-08",
        "nb_tracks": 0,
        "type": "single"
      },
      {
        "title": "Chemical",
        "label": "",
        "release_date": "2023-12-01",
        "nb_tracks": 0,
        "type": "single"
      },
      {
        "title": "Softcore",
        "label": "",
        "release_date": "2023-11-03",
        "nb_tracks": 0,
        "type": "single"
      }
    ],
    "related_artists": [
      "Saxena",
      "We Architects",
      "Revelries",
      "Switchblade",
      "Sam Smyers",
      "Saint.",
      "SRNDE",
      "Alberto Ciccarini",
      "Robin Tayger",
      "Ugg'A"
    ]
  },
  "genius": {
    "found": false,
    "raw": null,
    "status": "not_configured"
  },
  "discogs": {
    "found": false,
    "raw": null
  },
  "setlistfm": {
    "found": false,
    "raw": null,
    "status": "not_configured"
  },
  "lastfm": {
    "found": true,
    "raw": null,
    "name": "Lone Tusker",
    "mbid": "be37ed6a-4989-402f-9838-cef9e412f35e",
    "listeners": 125660,
    "playcount": 807117,
    "listener_play_ratio": 6.42,
    "bio_exists": false,
    "bio_summary": " <a href=\"https://www.last.fm/music/Lone+Tusker\">Read more on Last.fm</a>",
    "tags": [
      "electronic",
      "deep house",
      "Chill House"
    ],
    "similar_artists": [
      "Saxena",
      "Offmind",
      "Lost Frequencies",
      "TWOPILOTS",
      "Nu Aspect"
    ],
    "top_tracks": [
      {
        "name": "Sweater Weather",
        "listeners": 21796,
        "playcount": 47980
      },
      {
        "name": "Smooth Operator",
        "listeners": 21323,
        "playcount": 58193
      },
      {
        "name": "Wicked Game",
        "listeners": 20183,
        "playcount": 37624
      },
      {
        "name": "No Diggity",
        "listeners": 19417,
        "playcount": 40927
      },
      {
        "name": "Stumblin' In",
        "listeners": 18170,
        "playcount": 37833
      },
      {
        "name": "You're Somebody Else",
        "listeners": 14810,
        "playcount": 32510
      },
      {
        "name": "Crazy",
        "listeners": 13097,
        "playcount": 29924
      },
      {
        "name": "Locked Away",
        "listeners": 11552,
        "playcount": 19639
      },
      {
        "name": "Hey Now",
        "listeners": 11122,
        "playcount": 23819
      },
      {
        "name": "Bloom",
        "listeners": 8612,
        "playcount": 17418
      }
    ],
    "url": "https://www.last.fm/music/Lone+Tusker"
  },
  "bandsintown": {
    "found": false,
    "raw": null,
    "status": "not_configured"
  },
  "platforms_found": [
    "musicbrainz",
    "deezer",
    "lastfm"
  ],
  "platforms_missing": [
    "genius",
    "discogs",
    "setlistfm",
    "bandsintown"
  ],
  "platform_count": 3
}