{
  "artist_name": "Niriko",
  "artist_id": "niriko",
  "seed_source": {
    "origin": "pfc_playlist_scrape",
    "note": "Extracted from 37 PFC editorial playlists"
  },
  "enrichment_timestamp": "2026-02-09T16:02:57.979090+00:00",
  "musicbrainz": {
    "found": true,
    "raw": null,
    "mbid": "3bf2ce8b-62b1-44cf-8660-d7da5803b677",
    "type": "",
    "country": "",
    "area": "",
    "begin_date": "",
    "end_date": "",
    "gender": "",
    "genres": [],
    "aliases": [],
    "isnis": [],
    "ipis": [],
    "urls": {
      "free streaming": "https://open.spotify.com/artist/249Q1LZa29XL7XIatTN45M",
      "soundcloud": "https://soundcloud.com/niriko-music",
      "streaming": "https://music.apple.com/gb/artist/1768558597"
    },
    "labels": [
      "Chill Lemon"
    ],
    "disambiguation_confidence": "high"
  },
  "deezer": {
    "found": true,
    "raw": null,
    "deezer_id": 282062051,
    "name": "Niriko",
    "nb_fan": 9,
    "nb_album": 31,
    "link": "https://www.deezer.com/artist/282062051",
    "picture_url": "https://cdn-images.dzcdn.net/images/artist/8cdf2ac6416660f69edb98d78eca2bbd/250x250-000000-80-0-0.jpg",
    "labels": [],
    "contributors": [],
    "contributor_roles": {},
    "track_titles": [
      "Right Here",
      "Falling Faster",
      "New",
      "Lift Off",
      "Reboot"
    ],
    "track_durations": [
      161,
      142,
      175,
      166,
      141
    ],
    "track_ranks": [
      31066,
      298020,
      132098,
      146960,
      117233
    ],
    "has_explicit": false,
    "album_types": {
      "single": 31
    },
    "albums": [
      {
        "title": "Last Night",
        "label": "",
        "release_date": "2026-02-08",
        "nb_tracks": 0,
        "type": "single"
      },
      {
        "title": "Juice",
        "label": "",
        "release_date": "2026-01-11",
        "nb_tracks": 0,
        "type": "single"
      },
      {
        "title": "Midday",
        "label": "",
        "release_date": "2025-12-21",
        "nb_tracks": 0,
        "type": "single"
      },
      {
        "title": "Ripple",
        "label": "",
        "release_date": "2025-11-16",
        "nb_tracks": 0,
        "type": "single"
      },
      {
        "title": "Crush",
        "label": "",
        "release_date": "2025-09-21",
        "nb_tracks": 0,
        "type": "single"
      },
      {
        "title": "Stay Cool",
        "label": "",
        "release_date": "2025-09-07",
        "nb_tracks": 0,
        "type": "single"
      },
      {
        "title": "Sipping",
        "label": "",
        "release_date": "2025-08-24",
        "nb_tracks": 0,
        "type": "single"
      },
      {
        "title": "Move On",
        "label": "",
        "release_date": "2025-08-10",
        "nb_tracks": 0,
        "type": "single"
      },
      {
        "title": "Heat",
        "label": "",
        "release_date": "2025-07-27",
        "nb_tracks": 0,
        "type": "single"
      },
      {
        "title": "Twist",
        "label": "",
        "release_date": "2025-07-13",
        "nb_tracks": 0,
        "type": "single"
      },
      {
        "title": "Blink",
        "label": "",
        "release_date": "2025-06-29",
        "nb_tracks": 0,
        "type": "single"
      },
      {
        "title": "Rolling",
        "label": "",
        "release_date": "2025-06-15",
        "nb_tracks": 0,
        "type": "single"
      },
      {
        "title": "Barefoot",
        "label": "",
        "release_date": "2025-06-01",
        "nb_tracks": 0,
        "type": "single"
      },
      {
        "title": "Move with Me",
        "label": "",
        "release_date": "2025-05-18",
        "nb_tracks": 0,
        "type": "single"
      },
      {
        "title": "Glide",
        "label": "",
        "release_date": "2025-04-27",
        "nb_tracks": 0,
        "type": "single"
      },
      {
        "title": "New Number",
        "label": "",
        "release_date": "2025-04-13",
        "nb_tracks": 0,
        "type": "single"
      },
      {
        "title": "Level",
        "label": "",
        "release_date": "2025-03-30",
        "nb_tracks": 0,
        "type": "single"
      },
      {
        "title": "Tonight",
        "label": "",
        "release_date": "2025-03-16",
        "nb_tracks": 0,
        "type": "single"
      },
      {
        "title": "New",
        "label": "",
        "release_date": "2025-03-02",
        "nb_tracks": 0,
        "type": "single"
      },
      {
        "title": "Reboot",
        "label": "",
        "release_date": "2025-02-16",
        "nb_tracks": 0,
        "type": "single"
      },
      {
        "title": "Lift Off",
        "label": "",
        "release_date": "2025-02-02",
        "nb_tracks": 0,
        "type": "single"
      },
      {
        "title": "Right Here",
        "label": "",
        "release_date": "2025-01-19",
        "nb_tracks": 0,
        "type": "single"
      },
      {
        "title": "Feeling Good",
        "label": "",
        "release_date": "2025-01-05",
        "nb_tracks": 0,
        "type": "single"
      },
      {
        "title": "Margarita Nights",
        "label": "",
        "release_date": "2024-12-22",
        "nb_tracks": 0,
        "type": "single"
      },
      {
        "title": "Hugs",
        "label": "",
        "release_date": "2024-12-08",
        "nb_tracks": 0,
        "type": "single"
      },
      {
        "title": "First Move",
        "label": "",
        "release_date": "2024-11-24",
        "nb_tracks": 0,
        "type": "single"
      },
      {
        "title": "Falling Faster",
        "label": "",
        "release_date": "2024-11-10",
        "nb_tracks": 0,
        "type": "single"
      },
      {
        "title": "Ease",
        "label": "",
        "release_date": "2024-10-27",
        "nb_tracks": 0,
        "type": "single"
      },
      {
        "title": "Feel It",
        "label": "",
        "release_date": "2024-10-13",
        "nb_tracks": 0,
        "type": "single"
      },
      {
        "title": "Sand",
        "label": "",
        "release_date": "2024-09-29",
        "nb_tracks": 0,
        "type": "single"
      }
    ],
    "related_artists": []
  },
  "genius": {
    "found": false,
    "raw": null,
    "status": "not_configured"
  },
  "discogs": {
    "found": true,
    "raw": null,
    "discogs_id": 16356955,
    "name": "Niriko",
    "profile": "Lead guitar player from Madagascar.",
    "realname": "",
    "social_urls": [],
    "members": [],
    "groups": [
      "Tsy An-Jaza"
    ],
    "data_quality": "Needs Vote",
    "physical_releases": 1,
    "digital_only_releases": 0,
    "total_releases": 1,
    "formats": [
      "CD, Album"
    ],
    "labels": [
      "Earthworks, Stern's Music"
    ]
  },
  "setlistfm": {
    "found": false,
    "raw": null,
    "status": "not_configured"
  },
  "lastfm": {
    "found": true,
    "raw": null,
    "name": "Niriko",
    "mbid": "",
    "listeners": 25512,
    "playcount": 146999,
    "listener_play_ratio": 5.76,
    "bio_exists": false,
    "bio_summary": " <a href=\"https://www.last.fm/music/Niriko\">Read more on Last.fm</a>",
    "tags": [],
    "similar_artists": [
      "Rick Groove",
      "moe sizzle",
      "Sean Rivers",
      "Pello Esso",
      "Martin Bloumy"
    ],
    "top_tracks": [
      {
        "name": "Lift Off",
        "listeners": 10559,
        "playcount": 26572
      },
      {
        "name": "Glide",
        "listeners": 6158,
        "playcount": 12530
      },
      {
        "name": "Rolling",
        "listeners": 6077,
        "playcount": 11897
      },
      {
        "name": "Move with Me",
        "listeners": 5267,
        "playcount": 10825
      },
      {
        "name": "Reboot",
        "listeners": 5222,
        "playcount": 11577
      },
      {
        "name": "Falling Faster",
        "listeners": 3619,
        "playcount": 8438
      },
      {
        "name": "Right Here",
        "listeners": 3580,
        "playcount": 8138
      },
      {
        "name": "Ease",
        "listeners": 3519,
        "playcount": 7935
      },
      {
        "name": "Tonight",
        "listeners": 3292,
        "playcount": 6785
      },
      {
        "name": "New Number",
        "listeners": 3285,
        "playcount": 7162
      }
    ],
    "url": "https://www.last.fm/music/Niriko"
  },
  "bandsintown": {
    "found": false,
    "raw": null,
    "status": "not_configured"
  },
  "platforms_found": [
    "musicbrainz",
    "deezer",
    "discogs",
    "lastfm"
  ],
  "platforms_missing": [
    "genius",
    "setlistfm",
    "bandsintown"
  ],
  "platform_count": 4
}