{
  "artist_name": "Sid Southside",
  "artist_id": "sid_southside",
  "seed_source": {
    "origin": "pfc_playlist_scrape",
    "note": "Extracted from 37 PFC editorial playlists"
  },
  "enrichment_timestamp": "2026-02-09T17:02:07.226679+00:00",
  "musicbrainz": {
    "found": true,
    "raw": null,
    "mbid": "4c43fe32-d649-4df4-b5a3-f14174206623",
    "type": "Person",
    "country": "",
    "area": "",
    "begin_date": "",
    "end_date": "",
    "gender": "",
    "genres": [
      "hip hop",
      "instrumental",
      "boom bap",
      "chillwave",
      "instrumental hip hop",
      "lo-fi",
      "lo-fi hip hop",
      "downtempo"
    ],
    "aliases": [],
    "isnis": [],
    "ipis": [],
    "urls": {
      "free streaming": "https://www.deezer.com/artist/176203347",
      "purchase for download": "https://music.apple.com/us/artist/1634038452",
      "soundcloud": "https://soundcloud.com/sidsouthside",
      "streaming": "https://tidal.com/artist/33172934",
      "youtube music": "https://music.youtube.com/channel/UCY7EwbbGQ_gulR5FAMPhWlA"
    },
    "labels": [
      "Chill Caterpillar"
    ],
    "disambiguation_confidence": "high"
  },
  "deezer": {
    "found": true,
    "raw": null,
    "deezer_id": 176203347,
    "name": "Sid Southside",
    "nb_fan": 6,
    "nb_album": 21,
    "link": "https://www.deezer.com/artist/176203347",
    "picture_url": "https://cdn-images.dzcdn.net/images/artist/f3d5c55aec1678293eab74bb1576db01/250x250-000000-80-0-0.jpg",
    "labels": [],
    "contributors": [],
    "contributor_roles": {},
    "track_titles": [
      "Dayjob Dreamer"
    ],
    "track_durations": [
      148
    ],
    "track_ranks": [
      26620
    ],
    "has_explicit": false,
    "album_types": {
      "single": 21
    },
    "albums": [
      {
        "title": "fleeting time",
        "label": "",
        "release_date": "2026-02-08",
        "nb_tracks": 0,
        "type": "single"
      },
      {
        "title": "Proof in the Pudding",
        "label": "",
        "release_date": "2025-10-19",
        "nb_tracks": 0,
        "type": "single"
      },
      {
        "title": "Solitaire",
        "label": "",
        "release_date": "2025-10-05",
        "nb_tracks": 0,
        "type": "single"
      },
      {
        "title": "Sally",
        "label": "",
        "release_date": "2025-09-14",
        "nb_tracks": 0,
        "type": "single"
      },
      {
        "title": "Street Signs",
        "label": "",
        "release_date": "2025-08-31",
        "nb_tracks": 0,
        "type": "single"
      },
      {
        "title": "Penguin Dance",
        "label": "",
        "release_date": "2025-08-17",
        "nb_tracks": 0,
        "type": "single"
      },
      {
        "title": "back to back",
        "label": "",
        "release_date": "2025-08-03",
        "nb_tracks": 0,
        "type": "single"
      },
      {
        "title": "pharoah vibes",
        "label": "",
        "release_date": "2025-07-20",
        "nb_tracks": 0,
        "type": "single"
      },
      {
        "title": "last rights",
        "label": "",
        "release_date": "2025-07-06",
        "nb_tracks": 0,
        "type": "single"
      },
      {
        "title": "pals",
        "label": "",
        "release_date": "2025-06-22",
        "nb_tracks": 0,
        "type": "single"
      },
      {
        "title": "Tuesday Morning",
        "label": "",
        "release_date": "2025-06-08",
        "nb_tracks": 0,
        "type": "single"
      },
      {
        "title": "Red Flames",
        "label": "",
        "release_date": "2024-05-31",
        "nb_tracks": 0,
        "type": "single"
      },
      {
        "title": "Dumpling Sauce",
        "label": "",
        "release_date": "2023-10-22",
        "nb_tracks": 0,
        "type": "single"
      },
      {
        "title": "Cherry Blossom Harvest",
        "label": "",
        "release_date": "2023-07-16",
        "nb_tracks": 0,
        "type": "single"
      },
      {
        "title": "Dayjob Dreamer",
        "label": "",
        "release_date": "2023-07-09",
        "nb_tracks": 0,
        "type": "single"
      },
      {
        "title": "A Leaf on the Pavement",
        "label": "",
        "release_date": "2023-06-11",
        "nb_tracks": 0,
        "type": "single"
      },
      {
        "title": "Hazel Eyes",
        "label": "",
        "release_date": "2023-04-09",
        "nb_tracks": 0,
        "type": "single"
      },
      {
        "title": "Dance Closer",
        "label": "",
        "release_date": "2022-08-21",
        "nb_tracks": 0,
        "type": "single"
      },
      {
        "title": "Mornings with Oscar",
        "label": "",
        "release_date": "2022-08-07",
        "nb_tracks": 0,
        "type": "single"
      },
      {
        "title": "Feelin' Good Tonight",
        "label": "",
        "release_date": "2022-07-24",
        "nb_tracks": 0,
        "type": "single"
      },
      {
        "title": "The Way She Moves",
        "label": "",
        "release_date": "2022-07-17",
        "nb_tracks": 0,
        "type": "single"
      }
    ],
    "related_artists": []
  },
  "genius": {
    "found": false,
    "raw": null,
    "status": "not_configured"
  },
  "discogs": {
    "found": true,
    "raw": null,
    "discogs_id": 2868991,
    "name": "Thugz From Da SouthSide",
    "profile": "",
    "realname": "",
    "social_urls": [],
    "members": [
      "Nigaro",
      "Pimp Teddy",
      "Lil Corb",
      "Total Kayos"
    ],
    "groups": [],
    "data_quality": "Needs Major Changes",
    "physical_releases": 3,
    "digital_only_releases": 3,
    "total_releases": 6,
    "formats": [
      "",
      "12\", EP",
      "CDr, Album",
      "CDr, Mixtape, Sli"
    ],
    "labels": [
      "Kami Kaze Productions",
      "Trump Tight Mixtapes"
    ]
  },
  "setlistfm": {
    "found": false,
    "raw": null,
    "status": "not_configured"
  },
  "lastfm": {
    "found": true,
    "raw": null,
    "name": "Sid Southside",
    "mbid": "4c43fe32-d649-4df4-b5a3-f14174206623",
    "listeners": 88390,
    "playcount": 283164,
    "listener_play_ratio": 3.2,
    "bio_exists": false,
    "bio_summary": " <a href=\"https://www.last.fm/music/Sid+Southside\">Read more on Last.fm</a>",
    "tags": [
      "chill",
      "lofi",
      "Lo-Fi"
    ],
    "similar_artists": [
      "mutedvibes",
      "Zupa Fitz",
      "Fya Playce",
      "herbstreit",
      "louke's beats"
    ],
    "top_tracks": [
      {
        "name": "You Look Pretty",
        "listeners": 32720,
        "playcount": 66681
      },
      {
        "name": "back to back",
        "listeners": 19741,
        "playcount": 42665
      },
      {
        "name": "Hazel Eyes",
        "listeners": 15969,
        "playcount": 33296
      },
      {
        "name": "Feelin' Good Tonight",
        "listeners": 15807,
        "playcount": 35933
      },
      {
        "name": "When I Get A Lil' Older",
        "listeners": 14662,
        "playcount": 28348
      },
      {
        "name": "Birds in a Tree",
        "listeners": 11059,
        "playcount": 19611
      },
      {
        "name": "Dumpling Sauce",
        "listeners": 9417,
        "playcount": 18334
      },
      {
        "name": "pharoah vibes",
        "listeners": 7279,
        "playcount": 15897
      },
      {
        "name": "Dayjob Dreamer",
        "listeners": 6031,
        "playcount": 12284
      },
      {
        "name": "Swimming with You",
        "listeners": 3459,
        "playcount": 7283
      }
    ],
    "url": "https://www.last.fm/music/Sid+Southside"
  },
  "bandsintown": {
    "found": false,
    "raw": null,
    "status": "not_configured"
  },
  "platforms_found": [
    "musicbrainz",
    "deezer",
    "discogs",
    "lastfm"
  ],
  "platforms_missing": [
    "genius",
    "setlistfm",
    "bandsintown"
  ],
  "platform_count": 4
}